ripple_down_rules/__init__.py
ripple_down_rules/experts.py
ripple_down_rules/failures.py
ripple_down_rules/helpers.py
ripple_down_rules/predicates.py
ripple_down_rules/rdr.py
ripple_down_rules/rdr_decorators.py
ripple_down_rules/rules.py
ripple_down_rules/start-code-server.sh
ripple_down_rules/types.py
ripple_down_rules/utils.py
ripple_down_rules/datastructures/__init__.py
ripple_down_rules/datastructures/callable_expression.py
ripple_down_rules/datastructures/case.py
ripple_down_rules/datastructures/dataclasses.py
ripple_down_rules/datastructures/enums.py
ripple_down_rules/datastructures/field_info.py
ripple_down_rules/datastructures/tracked_object.py
ripple_down_rules/user_interface/__init__.py
ripple_down_rules/user_interface/gui.py
ripple_down_rules/user_interface/ipython_custom_shell.py
ripple_down_rules/user_interface/object_diagram.py
ripple_down_rules/user_interface/prompt.py
ripple_down_rules/user_interface/template_file_creator.py
ripple_down_rules-0.7.1.dist-info/licenses/LICENSE
ripple_down_rules-0.7.1.dist-info/METADATA
ripple_down_rules-0.7.1.dist-info/WHEEL
ripple_down_rules-0.7.1.dist-info/top_level.txt
ripple_down_rules-0.7.1.dist-info/RECORD
