Metadata-Version: 2.4
Name: ripple_down_rules
Version: 0.7.1
Summary: Implements the various versions of Ripple Down Rules (RDR) for knowledge representation and reasoning.
Author-email: Abdelrhman Bassiouny <abassiou@uni-bremen.de>
License:                     GNU GENERAL PUBLIC LICENSE
Project-URL: Homepage, https://github.com/AbdelrhmanBassiouny/ripple_down_rules
Keywords: robotics,knowledge,reasoning,representation
Classifier: Programming Language :: Python :: 3
License-File: LICENSE
Requires-Dist: anytree>=2.8.0
Requires-Dist: ordered_set>=4
Requires-Dist: pygraphviz>=1.7
Requires-Dist: typing-extensions>=4.12.2
Requires-Dist: graphviz
Requires-Dist: tabulate
Requires-Dist: ipython
Requires-Dist: requests
Requires-Dist: colorama
Requires-Dist: pygments
Requires-Dist: sqlalchemy
Requires-Dist: pandas
Requires-Dist: pyparsing>=3.2.3
Requires-Dist: omegaconf
Requires-Dist: rustworkx
Requires-Dist: pydot
Provides-Extra: viz
Requires-Dist: networkx>=3.1; extra == "viz"
Requires-Dist: matplotlib>=3.7.5; extra == "viz"
Provides-Extra: gui
Requires-Dist: pyqt6; extra == "gui"
Requires-Dist: qtconsole; extra == "gui"
Dynamic: license-file
